TrainSense/__init__.py
TrainSense/analyzer.py
TrainSense/arch_analyzer.py
TrainSense/deep_analyzer.py
TrainSense/gpu_monitor.py
TrainSense/gradient_analyzer.py
TrainSense/integrations.py
TrainSense/logger.py
TrainSense/model_profiler.py
TrainSense/monitoring.py
TrainSense/optimizer.py
TrainSense/performance_tuner.py
TrainSense/system_config.py
TrainSense/system_diagnostics.py
TrainSense/ultra_optimizer.py
TrainSense/utils.py
TrainSense/visualizer.py
trainsense-0.5.1.dist-info/METADATA
trainsense-0.5.1.dist-info/WHEEL
trainsense-0.5.1.dist-info/top_level.txt
trainsense-0.5.1.dist-info/RECORD
