Metadata-Version: 2.4
Name: TrainSense
Version: 0.5.1
Summary: Toolkit for PyTorch model analysis, profiling, and training optimization.
Home-page: https://github.com/RDTvlokip/TrainSense
Author: RDTvlokip
Author-email: rdtvlokip@gmail.com
License: MIT
Project-URL: Bug Tracker, https://github.com/RDTvlokip/TrainSense/issues
Project-URL: Source Code, https://github.com/RDTvlokip/TrainSense
Keywords: pytorch,torch,deep learning,machine learning,ai,profiling,profiler,performance,optimization,analysis,diagnostics,monitoring,gpu,cuda,nvidia,memory usage,gradients,training,debugging,developer tools,mlops,hyperparameters,dataloader,trainsense,hyperparameter tuning,transformers,explainability
Classifier: Development Status :: 4 - Beta
Classifier: Intended Audience :: Developers
Classifier: Intended Audience :: Science/Research
Classifier: License :: OSI Approved :: MIT License
Classifier: Operating System :: OS Independent
Classifier: Programming Language :: Python :: 3
Classifier: Programming Language :: Python :: 3.7
Classifier: Programming Language :: Python :: 3.8
Classifier: Programming Language :: Python :: 3.9
Classifier: Programming Language :: Python :: 3.10
Classifier: Programming Language :: Python :: 3.11
Classifier: Programming Language :: Python :: 3.12
Classifier: Topic :: Scientific/Engineering :: Artificial Intelligence
Classifier: Topic :: Software Development :: Libraries :: Python Modules
Classifier: Topic :: System :: Monitoring
Classifier: Topic :: Utilities
Classifier: Typing :: Typed
Requires-Python: >=3.7
Requires-Dist: psutil>=5.8.0
Requires-Dist: torch>=1.8.0
Requires-Dist: GPUtil>=1.4.0
Provides-Extra: plotting
Requires-Dist: matplotlib>=3.3.0; extra == "plotting"
Requires-Dist: numpy; extra == "plotting"
Provides-Extra: html
Requires-Dist: jinja2>=3.0.0; extra == "html"
Provides-Extra: trl
Requires-Dist: transformers>=4.0.0; extra == "trl"
Provides-Extra: dev
Requires-Dist: pytest>=6.0; extra == "dev"
Requires-Dist: flake8>=3.8; extra == "dev"
Requires-Dist: black>=21.0b0; extra == "dev"
Requires-Dist: coverage>=5.0; extra == "dev"
Requires-Dist: mypy>=0.900; extra == "dev"
Requires-Dist: ipykernel; extra == "dev"
Provides-Extra: all
Requires-Dist: matplotlib>=3.3.0; extra == "all"
Requires-Dist: numpy; extra == "all"
Requires-Dist: jinja2>=3.0.0; extra == "all"
Requires-Dist: transformers>=4.0.0; extra == "all"
Dynamic: author
Dynamic: author-email
Dynamic: classifier
Dynamic: description
Dynamic: description-content-type
Dynamic: home-page
Dynamic: keywords
Dynamic: license
Dynamic: project-url
Dynamic: provides-extra
Dynamic: requires-dist
Dynamic: requires-python
Dynamic: summary
